notion_to_md/__init__.py
notion_to_md/notion_to_md.py
notion_to_md/types/__init__.py
notion_to_md/types/notion_types.py
notion_to_md/utils/__init__.py
notion_to_md/utils/md.py
notion_to_md/utils/notion.py
tests/__init__.py
tests/test_md.py
tests/test_notion_to_md.py
notion_to_md_py-0.1.4.dist-info/LICENSE
notion_to_md_py-0.1.4.dist-info/METADATA
notion_to_md_py-0.1.4.dist-info/WHEEL
notion_to_md_py-0.1.4.dist-info/top_level.txt
notion_to_md_py-0.1.4.dist-info/RECORD
