Metadata-Version: 2.2
Name: notion-to-md-py
Version: 0.1.4
Summary: A package to convert Notion content into Markdown format
Home-page: https://github.com/SwordAndTea/notion-to-md-py
Author: Wei Xiang
Author-email: xiangweiqaz@gmail.com
Project-URL: Bug Tracker, https://github.com/SwordAndTea/notion-to-md-py/issues
Project-URL: Source Code, https://github.com/SwordAndTea/notion-to-md-py
Keywords: notion markdown converter python
Classifier: Programming Language :: Python :: 3.7
Classifier: License :: OSI Approved :: MIT License
Classifier: Operating System :: OS Independent
Requires-Python: >=3.7
License-File: LICENSE
Requires-Dist: httpx
Requires-Dist: pytablewriter
Requires-Dist: notion-client
Provides-Extra: async
Requires-Dist: asyncio; extra == "async"
Dynamic: author
Dynamic: author-email
Dynamic: classifier
Dynamic: description
Dynamic: description-content-type
Dynamic: home-page
Dynamic: keywords
Dynamic: project-url
Dynamic: provides-extra
Dynamic: requires-dist
Dynamic: requires-python
Dynamic: summary
